{
  "build/dist/material-ui-pickers.cjs.js": {
    "bundled": 128721,
    "minified": 73963,
    "gzipped": 14932
  },
  "build/dist/material-ui-pickers.esm.js": {
    "bundled": 127801,
    "minified": 73226,
    "gzipped": 14850,
    "treeshaked": {
      "rollup": {
        "code": 52128,
        "import_statements": 1341
      },
      "webpack": {
        "code": 55181
      }
    }
  },
  "build/dist/material-ui-pickers.umd.js": {
    "bundled": 840868,
    "minified": 324623,
    "gzipped": 78199
  },
  "build/dist/material-ui-pickers.umd.min.js": {
    "bundled": 716567,
    "minified": 285287,
    "gzipped": 70085
  },
  "build/index.js": {
    "bundled": 127779,
    "minified": 73210,
    "gzipped": 14835,
    "treeshaked": {
      "rollup": {
        "code": 52112,
        "import_statements": 1341
      },
      "webpack": {
        "code": 55165
      }
    }
  },
  "build/build/dist/material-ui-pickers.esm.js": {
    "bundled": 127801,
    "minified": 73226,
    "gzipped": 14850,
    "treeshaked": {
      "rollup": {
        "code": 52128,
        "import_statements": 1341
      },
      "webpack": {
        "code": 55181
      }
    }
  }
}
